canonicalwebteam/__init__.py
canonicalwebteam/cookie_service/__init__.py
canonicalwebteam/cookie_service/client.py
canonicalwebteam/cookie_service/exceptions.py
canonicalwebteam/cookie_service/helpers.py
canonicalwebteam/cookie_service/routes.py
canonicalwebteam_cookie_service-1.0.5.dist-info/licenses/LICENSE
canonicalwebteam_cookie_service-1.0.5.dist-info/METADATA
canonicalwebteam_cookie_service-1.0.5.dist-info/WHEEL
canonicalwebteam_cookie_service-1.0.5.dist-info/top_level.txt
canonicalwebteam_cookie_service-1.0.5.dist-info/RECORD
