Metadata-Version: 2.4
Name: canonicalwebteam.cookie_service
Version: 1.0.5
Summary: Flask extension to integrate with shared cookie service.
Home-page: https://github.com/canonical/canonicalwebteam.cookie-service
Author: Canonical webteam
Author-email: webteam@canonical.com
License: LGPL-2.1
License-File: LICENSE
Requires-Dist: Flask>=1.0.2
Requires-Dist: requests>=2.20.0
Dynamic: author
Dynamic: author-email
Dynamic: description
Dynamic: description-content-type
Dynamic: home-page
Dynamic: license
Dynamic: license-file
Dynamic: requires-dist
Dynamic: summary
